stdontoday/__init__.py
stdontoday/module1.py
stdontoday-0.1.0.dist-info/LICENSE
stdontoday-0.1.0.dist-info/METADATA
stdontoday-0.1.0.dist-info/WHEEL
stdontoday-0.1.0.dist-info/top_level.txt
stdontoday-0.1.0.dist-info/RECORD
